[
  {
    "Patient_Id": "PT-2025-0001",
    "FirstName": "Sara",
    "LastName": "Ibrahim",
    "DateOfBirth": "1990-01-01",
    "Gender": "Female",
    "NationalId": "NID12345",
    "BloodType": "A+",
    "Allergies": "None",
    "ChrinicConditions": "None",
    "Address": "Cairo, Egypt",
    "EmergencyContactName": "Ahmed Ibrahim",
    "EmergencyContactPhone": "01000000010",
    "Status": "Active",
    "UserId": 5
  },
  {
    "Patient_Id": "PT-2025-0002",
    "FirstName": "Mariam",
    "LastName": "Ali",
    "DateOfBirth": "1992-05-12",
    "Gender": "Female",
    "NationalId": "NID12346",
    "BloodType": "B+",
    "Allergies": "Penicillin",
    "ChrinicConditions": "Asthma",
    "Address": "Alexandria, Egypt",
    "EmergencyContactName": "Ali Khaled",
    "EmergencyContactPhone": "01000000011",
    "Status": "Active",
    "UserId": 6
  },
  {
    "Patient_Id": "PT-2025-0003",
    "FirstName": "Youssef",
    "LastName": "Hany",
    "DateOfBirth": "1988-07-20",
    "Gender": "Male",
    "NationalId": "NID12347",
    "BloodType": "O+",
    "Allergies": "None",
    "ChrinicConditions": "Diabetes",
    "Address": "Giza, Egypt",
    "EmergencyContactName": "Hany Khaled",
    "EmergencyContactPhone": "01000000012",
    "Status": "Active",
    "UserId": 7
  }
]
